Workbook

Sheet Summary
A1: Commercial Personal Financial Statement
A2: Dated as of: | B2: 46295
A4: Individual Information
A5: Name | B5: Vartan Tchekmedyian
A6: Address | B6: 3045 Verdugo Road
A7: City, State, Zip | B7: Los Angeles, CA 90065
A8: Phone | B8: 714-878-1008
A9: Email | B9: vartan.tchekmedyian1@gmail.com
A11: Annual Income
A12: Source | B12: Amount
A13: Salary | B13: 350000
A14: Bonuses/Commission | B14: 210000
A15: Dividend/Interest (Scd E) | B15: =SUM('Sch E - Receivables'!C3:C14)
A16: Other (Scd C) | B16: ='Sch C - Real Estate'!U23
A17: Alimony/Child Support/Maintenance
A18: Total Annual Income | B18: =SUM(B13:B17)
A20: Assets | D20: Liabilities
A21: Cash On Hand (Schedule A) | B21: =SUM('Sch A - Cash'!C3:C23) | D21: Automobile Loans (Sch G) | E21: =SUMIF('Sch G - Liabilities'!A3:A30,"Auto",'Sch G - Liabilities'!F3:F30)
A22: Marketable Stocks/Bonds (Sch B) | B22: =SUMIF('Sch B - Securities'!A3:A22,"Marketable",'Sch B - Securities'!E3:E22) | D22: Lines of Credit (Sch G) | E22: =SUMIF('Sch G - Liabilities'!A3:A30,"LOC",'Sch G - Liabilities'!F3:F30)
A23: Other Securities (Sch B) | B23: =SUMIF('Sch B - Securities'!A3:A22,"Other",'Sch B - Securities'!E3:E22) | D23: Revolving Loan (Sch G) | E23: =SUMIF('Sch G - Liabilities'!A3:A30,"Revolv",'Sch G - Liabilities'!F3:F30)
A24: Personal Residence (Sch C) | B24: ='Sch C - Real Estate'!I25 | D24: Accounts Payable (Sch G) | E24: =SUMIF('Sch G - Liabilities'!A3:A30,"A/P",'Sch G - Liabilities'!F3:F30)
A25: Secondary Residence(s) (Sch C) | B25: 0 | D25: Accounts Payable - Related (Sch G) | E25: =SUMIF('Sch G - Liabilities'!A3:A30,"A/P Related",'Sch G - Liabilities'!F3:F30)
A26: Commercial RE / Income Prop (Sch C) | B26: ='Sch C - Real Estate'!I23 | D26: Other (Sch G) | E26: =SUMIF('Sch G - Liabilities'!A3:A30,"Other",'Sch G - Liabilities'!F3:F30)
A27: Unimproved Land (Sch C) | B27: 0 | D27: RE Loan - Residence(s) (Sch C) | E27: ='Sch C - Real Estate'!J25
A28: C Corporation (Sch D) | B28: =SUMIF('Sch D - Businesses'!A3:A17,"C Corp",'Sch D - Businesses'!E3:E17) | D28: RE Loan - Commercial (Sch C) | E28: ='Sch C - Real Estate'!J23
A29: S Corporation (Sch D) | B29: =SUMIF('Sch D - Businesses'!A3:A17,"S Corp",'Sch D - Businesses'!E3:E17) | D29: RE Loan - Unimproved Land (Sch C) | E29: 0
A30: Limited Liability Company (Sch D) | B30: =SUMIF('Sch D - Businesses'!A3:A17,"LLC",'Sch D - Businesses'!E3:E17) | D30: Personal Liabilities (Sch H) | E30: =SUMIF('Sch H - Other Liab'!A3:A12,"Personal",'Sch H - Other Liab'!F3:F12)
A31: General & Limited Partnerships (D) | B31: =SUMIF('Sch D - Businesses'!A3:A17,"Partnership",'Sch D - Businesses'!E3:E17) | D31: Other Liabilities (Sch H) | E31: =SUMIF('Sch H - Other Liab'!A3:A12,"Other",'Sch H - Other Liab'!F3:F12)
A32: Closely Held Businesses (Sch D) | B32: =SUMIF('Sch D - Businesses'!A3:A17,"Closely Held",'Sch D - Businesses'!E3:E17)
A33: Contracts/Accts/Notes Rec (Sch E) | B33: =SUMIF('Sch E - Receivables'!A3:A14,"A/R",'Sch E - Receivables'!F3:F14)
A34: Notes Rec - Related Party (Sch E) | B34: =SUMIF('Sch E - Receivables'!A3:A14,"A/R Related",'Sch E - Receivables'!F3:F14)
A35: Cash Surrender Value Life Ins (F) | B35: =SUMIF('Sch F - Other Assets'!A3:A14,"Life Insurance",'Sch F - Other Assets'!E3:E14)
A36: Retirement Accounts (Sch F) | B36: =SUMIF('Sch F - Other Assets'!A3:A14,"Retirement",'Sch F - Other Assets'!E3:E14)
A37: Personal / Other Assets (Sch F) | B37: =SUMIF('Sch F - Other Assets'!A3:A14,"Personal",'Sch F - Other Assets'!E3:E14)+SUMIF('Sch F - Other Assets'!A3:A14,"Other",'Sch F - Other Assets'!E3:E14)
A39: Total Assets | B39: =SUM(B21:B37) | D39: Total Liabilities | E39: =SUM(E21:E31)
D40: Net Worth | E40: =B39-E39
A41: Check: Assets = Liab + NW | B41: =B39-E39-E40 | D41: Total Liabilities & Net Worth | E41: =E39+E40

Sheet Sch A - Cash
A1: Schedule A: Cash, Savings, Certificates
A2: Name of Bank / Institution | B2: Type of Account | C2: Acct Balance | D2: S/J/T
A3: Schwab (Acct 8704-0675) | B3: Brokerage Cash (Free Credit) | C3: 361.71 | D3: S
A4: Columbia Bank - Embark Checking (Acct ...5297) | B4: Personal Checking | C4: 28804.57 | D4: S
A5: Columbia Bank - VT OH 100 LLC (...5932) | B5: Business Checking | C5: 195624.83 | D5: S
A6: Columbia Bank - VT 3045 LLC (...9568) | B6: Business Checking | C6: 5965.68 | D6: S
A7: Columbia Bank - VT 3021 LLC (...5079) | B7: Business Checking | C7: 5143.35 | D7: S
A8: Columbia Bank - VT 1277 LLC (...0709) | B8: Business Checking | C8: 22128.94 | D8: S
A9: Columbia Bank - VT 1207 LLC (...5344) | B9: Business Checking | C9: 60912.52 | D9: S
A10: Columbia Bank - VT 2021 LLC (...6841) | B10: Business Checking | C10: 4766.48 | D10: S
A11: Columbia Bank - VT 3011 LLC (...4419) | B11: Business Checking | C11: 6508.23 | D11: S
A12: Columbia Bank - VT 1992 LLC (...6320) | B12: Business Checking | C12: 11927.55 | D12: S
A13: Columbia Bank - VT 3400 LLC (...6844) | B13: Business Checking | C13: 1144.91 | D13: S
A14: Columbia Bank - VT 3149 LLC (...1808) | B14: Business Checking | C14: 742 | D14: S
... A23: Umpqua Bank - VT OH 100 LLC CD (...3408) | B23: Certificate of Deposit | C23: 55618.15 | D23: S
B24: Total | C24: =SUM(C3:C23)

Sheet Sch B - Securities
A1: Schedule B: Marketable / Closely Held Securities (attach statements)
A2: Category | B2: Description | C2: No. Shares | D2: Price / Share | E2: Total Value | F2: Pledged? | G2: In the Name of | H2: Broker | I2: S/J/T
A3: Marketable | B3: SUTXX - Schwab US Treasury Money Fund | C3: 1687977.3 | D3: 1 | E3: =C3*D3 | F3: No | G3: Vartan Tchekmedyian | H3: Schwab | I3: S
A4: Marketable | B4: Crypto (Coinbase, MetaMask, Trust Wallet) | C4: 1 | D4: =106724.9312+36425+8147.0188 | E4: =C4*D4 | F4: No | G4: Vartan Tchekmedyian | H4: Various | I4: S
A5: Marketable | B5: Fidelity Account | C5: 1 | D5: 495423.32 | E5: =C5*D5 | F5: No | G5: Vartan Tchekmedyian | H5: Fidelity | I5: S
E6: =C6*D6
E7: =C7*D7
E8: =C8*D8
E9: =C9*D9
E10: =C10*D10
E11: =C11*D11
E12: =C12*D12
E13: =C13*D13
E14: =C14*D14
E15: =C15*D15
E16: =C16*D16
E17: =C17*D17
... E22: =C22*D22
D23: Total | E23: =SUM(E3:E22)

Sheet Sch C - Real Estate
A1: Schedule C: Commercial Real Estate
J3: LOAN INFORMATION | Q3: PROPERTY CASH FLOW
A4: Property Address | B4: Property Type | C4: Square Feet | D4: # of Units | E4: % Owned | F4: Acquisition Date | G4: Cost | H4: Cap Rate | I4: Est. Market Value | J4: Loan Balance | K4: Current Equity | L4: Loan-to- Value | M4: Lender | N4: Maturity Date | O4: Interest Rate | P4: Recourse to Owner | Q4: Annual Gross Rents | R4: Annual Expenses | S4: Annual NOI | T4: Annual Debt Service | U4: Excess Cash Flow | V4: Improvements & Cash Invested | W4: Vested Owner | X4: Notes
A5: 3045 Verdugo Road LA CA 90065 | B5: Creative Office - SINGLE TENANT NNN LEASE | C5: 15300 | D5: 1 | E5: 100 | F5: 41501 | G5: =1200000+V5 | H5: =+S5/G5 | I5: 6180000 | Q5: =1.03*309000 | R5: 0 | S5: =+Q5-R5 | V5: 0 | W5: VT 3045 LLC
A6: 3021 Verdugo Road LA CA 90065 | B6: Creative Office - SINGLE TENANT NNN LEASE | C6: 5961 | D6: 1 | E6: 100 | F6: 42359 | G6: =V6+ 975000 | H6: =+S6/G6 | I6: 4681745 | Q6: =1.03*257496 | R6: 0 | S6: =+Q6-R6 | V6: 65000 | W6: VT 3021 LLC
A7: 3011 Verdugo Road LA CA 90065 | B7: Creative Office - SINGLE TENANT NNN LEASE | C7: 3200 | D7: 1 | E7: 100 | F7: 42515 | G7: =V7+ 900000 | H7: =+S7/G7 | I7: 2809091 | Q7: =1.03*154500 | R7: 0 | S7: =+Q7-R7 | V7: 100000 | W7: VT 3011 LLC
A8: 2920 Eagle Rock Blvd LA CA 90065 | B8: Creative Office - SINGLE TENANT NNN LEASE | C8: 1100 | D8: 1 | E8: 100 | F8: 43409 | G8: =V8+ 1700000 | H8: =+S8/G8 | I8: 1700000 | J8: 486129 | K8: =I8-J8 | L8: =(J8/I8) | M8: SELLER FINANCED | N8: 49820 | O8: 0.0475 | P8: YES | Q8: =1.03*154500 | R8: 0 | S8: =+Q8-R8 | T8: =5234.21*12 | U8: =+S8-T8 | V8: 49000 | W8: VT 2021 LLC
J9: 5300929 | M9: UMPQUA | N9: 48523 | O9: 0.05 | P9: YES | T9: 353952
J10: 3062570 | M10: UMPQUA | N10: 47092 | O10: 0.0499 | P10: YES | T10: 225120
J11: 672000 | M11: SBA EIDL | N11: 55476 | O11: 0.0375 | P11: YES | T11: =3460*12
J12: 145000 | M12: SBA EIDL | N12: 55600 | O12: 0.0375 | P12: YES | T12: =747*12
A13: VERDUGO PORTFOLIO | B13: Creative Office - SINGLE TENANT NNN LEASE | C13: =SUM(C5:C8) | D13: =SUM(D5:D8) | E13: 100 | G13: =SUM(G5:G8) | H13: =+S13/G13 | I13: =SUM(I5:I8) | J13: =SUM(J5:J12) | K13: =I13-J13 | L13: =(J13/I13) | Q13: =SUM(Q5:Q12) | R13: =SUM(R5:R12) | S13: =SUM(S5:S12) | T13: =SUM(T5:T12) | U13: =+S13-T13 | V13: =SUM(V5:V12)
A14: 1201-1217 Cypress Ave LA CA 90065 | B14: Mixed Use | C14: 10600 | D14: 11 | E14: 93 | F14: 43648 | G14: =V14+ 2900000 | H14: =+S14/G14 | I14: 6000000 | J14: 3268815 | K14: =I14-J14 | L14: =J14/I14 | M14: UMPQUA | N14: 48204 | O14: 0.035 | P14: YES | Q14: 594133 | R14: 131224 | S14: =+Q14-R14 | T14: =12*(10544+8336) | U14: =+S14-T14 | V14: =847449+83101+416258.58 | W14: VT 1207 LLC
A15: 3149 Verdugo Road LA CA 90065 | B15: Creative Office | C15: 3600 | D15: 1 | E15: 100 | F15: 44725 | G15: =V15+ 1350000 | H15: =+S15/G15 | I15: 2700000 | J15: 1470905 | K15: =I15-J15 | L15: =J15/I15 | M15: UMPQUA | N15: 48823 | O15: 0.0576 | P15: YES | Q15: =12600*12 | R15: 0 | S15: =+Q15-R15 | T15: =9929*12 | U15: =+S15-T15 | V15: 400000 | W15: VT 3149 LLC
A16: 1974-1992 Lincoln Ave Pasadena CA 91103 | B16: Retail | C16: 7004 | D16: 4 | E16: 100 | F16: 45002 | G16: =V16+ 4162235 | H16: =+S16/G16 | I16: 4700000 | J16: 1461625 | K16: =I16-J16 | L16: =J16/I16 | M16: CHASE | N16: 46478 | O16: 0.0371 | P16: NO | Q16: =(20952+6556)*12 | R16: =43255+30876+2170+4980+5970+3628+11880+8700 | S16: =+Q16-R16 | T16: =7373.58*12 | U16: =+S16-T16 | V16: 130000 | W16: VT 1992 LLC
A17: 1277-1279 Cypress Ave Los Angeles CA 90065 | B17: Retail | C17: 2400 | D17: 2 | E17: 82 | F17: 45458 | G17: =V17+ 688000 | H17: =+S17/G17 | I17: 1200000 | K17: =I17-J17 | Q17: =(2813+5250)*12 | R17: 15000 | S17: =+Q17-R17 | U17: =+S17-T17 | V17: 60000 | W17: VT 1277 LLC
A18: 100 E Broad St Columbus OH 43215 | B18: Office | C18: 364296 | D18: 40+ | E18: 100 | F18: 45761 | G18: 3400000 | H18: =+S18/G18 | I18: 6000000 | K18: =I18-J18 | Q18: 2031618 | R18: 1921843 | S18: =+Q18-R18 | U18: =+S18-T18 | W18: VT OH 100 LLC
A19: 712-826 Glendale Ave Glendale CA 91206 | B19: Mixed Use | C19: 51798 | D19: 31 | E19: 100 | F19: 46006 | G19: 24750000 | H19: =+S19/G19 | I19: 40000000 | J19: 19532509 | K19: =I19-J19 | Q19: 1000000 | R19: 573600 | S19: =+Q19-R19 | U19: =+S19-T19 | W19: VT 826 LLC
A20: 2709 Ave 34 Los Angeles CA 90065 | B20: Mixed Use | C20: 5715 | D20: 4 | E20: 72.4 | F20: 46073 | G20: 800000 | H20: =+S20/G20 | I20: 1100000 | K20: =I20-J20 | Q20: =10540*12 | R20: 17000 | S20: =+Q20-R20 | U20: =+S20-T20 | W20: VT 2709 LLC
A21: 2705 Ave 34 Los Angeles CA 90065 | B21: Commercial | C21: 2200 | D21: 1 | E21: 72.4 | F21: 46073 | G21: 1375000 | H21: =+S21/G21 | I21: 1300000 | K21: =I21-J21 | Q21: =4500*12 | R21: 25000 | S21: =+Q21-R21 | U21: =+S21-T21 | W21: VT 2705 LLC
A22: 2100 Cypress Ave Los Angeles CA 90065 | B22: Bar | C22: 3800 | E22: 70 | F22: 46219 | G22: 2500000 | H22: =+S22/G22 | I22: 2500000 | K22: =I22-J22 | Q22: =19000*12 | S22: =+Q22-R22 | U22: =+S22-T22 | W22: VT 2100 LLC
A23: Total: | C23: =SUM(C13:C22) | G23: =SUM(G13:G22) | I23: =SUM(I13:I22) | J23: =SUM(J13:J22) | K23: =SUM(K13:K22) | Q23: =SUM(Q13:Q22) | R23: =SUM(R13:R22) | S23: =SUM(S13:S22) | T23: =SUM(T13:T22) | U23: =SUM(U13:U22) | V23: =SUM(V13:V22)
A24: Personal Residence (not included in commercial total above)
A25: 375 Canyon Vista Dr, LA CA 90065 | B25: Residential | C25: 3800 | D25: 1 | E25: 100 | F25: 43829 | G25: 3100000 | I25: 4000000 | J25: 884822 | K25: =I25-J25 | L25: =J25/I25 | M25: Wells Fargo | N25: 46751 | O25: 0.025 | P25: YES | T25: 49311 | V25: 1800000 | W25: Vartan Tchekmedyian | X25: Primary residence

Sheet Sch D - Businesses
A1: Schedule D: Businesses Owned
A2: Category | B2: Name | C2: No. Shares | D2: Cost / Share | E2: Total Cost | F2: S/J/T
A3: C Corp | B3: Zamp Technologies | C3: 250000 | D3: 1 | E3: =C3*D3 | F3: S
A4: C Corp | B4: Ceartas | C4: 750000 | D4: 1 | E4: =C4*D4 | F4: S
A5: LLC | B5: Buckyball Intermediate | C5: 12359472 | D5: =15136532/C5 | E5: =C5*D5 | F5: S
E6: =C6*D6
E7: =C7*D7
E8: =C8*D8
E9: =C9*D9
E10: =C10*D10
E11: =C11*D11
E12: =C12*D12
E13: =C13*D13
E14: =C14*D14
E15: =C15*D15
E16: =C16*D16
E17: =C17*D17
D18: Total | E18: =SUM(E3:E17)

Sheet Sch E - Receivables
A1: Schedule E: Contracts / Accounts / Notes Receivable
A2: Type | B2: Owner(s) | C2: Pmt Amount | D2: Frequency | E2: Due From | F2: Balance Due | G2: Collateral | H2: Maturity Date | I2: S/J/T
A3: A/R | B3: Vartan Tchekmedyian | C3: =0.085*F3 | D3: Monthly | E3: Revenge Of Inc. | F3: 509174.72 | G3: 3420 Eagle Rock Blvd | H3: 46387 | I3: S
E15: Total | F15: =SUM(F3:F14)

Sheet Sch F - Other Assets
A1: Schedule F: Other Assets and Personal Property
A2: Category | B2: Description | C2: Notes | D2: Cost | E2: Current Value | F2: S/J/T
D15: Total | E15: =SUM(E3:E14)

Sheet Sch G - Liabilities
A1: Schedule G: Revolving / LOC / Auto / Accounts Payable / Other
A2: Type | B2: Owner(s) | C2: Pmt Amount | D2: Frequency | E2: Due To | F2: Balance Due | G2: Max Credit | H2: Collateral | I2: Maturity Date | J2: S/J/T
A3: Revolv | B3: Vartan Tchekmedyian | D3: Monthly | E3: Chase Sapphire (Personal) | F3: 952 | H3: Unsecured | J3: S
A4: Revolv | B4: Vartan Tchekmedyian | D4: Monthly | E4: American Express Platinum (...4002) | F4: 5819 | H4: Unsecured | J4: S
A5: Revolv | B5: Vartan Tchekmedyian | D5: Monthly | E5: American Express Business Platinum (...3004) | F5: 108725 | H5: Unsecured | J5: S
A6: Revolv | B6: Vartan Tchekmedyian | D6: Monthly | E6: American Express Business Centurion (...3006) | F6: 25743 | H6: Unsecured | J6: S
E31: Total | F31: =SUM(F3:F30)

Sheet Sch H - Other Liab
A1: Schedule H: Other Liabilities (Personal / Other)
A2: Type | B2: Owner(s) | C2: Pmt Amount | D2: Frequency | E2: Due To | F2: Balance Due | G2: Collateral | H2: Maturity Date | I2: S/J/T
E13: Total | F13: =SUM(F3:F12)

Sheet Contingent & Q
A1: Contingent Liabilities
A2: Type codes: 1 Guarantor/Endorser 2 Leases/Contracts 3 Legal Claims/Judgments 4 Income Tax Claim 5 Standby LOC 6 Other
A4: Primary Obligor | B4: Terms of Payment | C4: Due To | D4: Maturity Date | E4: Max Legal Obligation | F4: Honor? Y/N | G4: Type (1-6)
A16: Questionnaire
A17: Question | B17: Y/N | C17: Details
A18: Do you have home insurance?
A19: Do you have life insurance?
A20: Have you made a will?
A21: Have you established a trust?
A22: Any suits / unsatisfied judgments against you?
A23: Have you ever declared bankruptcy?
A24: Do you have a CPA?
A25: Do you have an Attorney?
